{
  "users": [
    {"id": 1, "name": "Marcelo Chávez", "username": "mchavez", "email": "marcelo.chavez07@gmail.com", "image": "https://i.ibb.co/ZH7356D/cody.jpg"},
    {"id": 2, "name": "Marcelo Chávez Vicencio", "username": "mchavezv", "email": "marcelo.chavez08@gmail.com", "image": "https://i.ibb.co/ZH7356D/cody.jpg"},
    {"id": 3, "name": "Marcelo Nahum Chávez Vicencio", "username": "mnchavezv", "email": "marcelo.chavez09@gmail.com", "image": "https://i.ibb.co/ZH7356D/cody.jpg"}
  ],
  "posts": [
    { "id": 1, "title": "Hola", "body": "como estás? 1", "UserId": 1},
    { "id": 2, "title": "Hello", "body": "como estás? 2", "UserId": 1},
    { "id": 3, "title": "Hi", "body": "como estás? 3", "UserId": 2},
    { "id": 3, "title": "Olá", "body": "como estás? 4", "UserId": 3},
    { "id": 3, "title": "Ciao", "body": "como estás? 5", "UserId": 3},
    { "id": 3, "title": "Jelou", "body": "como estás? 6", "UserId": 3}
  ],
  "comments": [
    { "id": 1, "body": "some comment", "postId": 1 },
    { "id": 2, "body": "some comment", "postId": 1 }
  ]
}
